libro/__init__.py
libro/_version.py
libro-0.1.26.dist-info/METADATA
libro-0.1.26.dist-info/WHEEL
libro-0.1.26.dist-info/RECORD
